<?xml version="1.0" encoding="utf-8"?>
<Messages>
	<Message severity="INFO" prefix="[HLS 200-111]" key="HLS_111_966" tag="RUNTIME" content="Finished File checks and directory preparation: CPU user time: 0 seconds. CPU system time: 0 seconds. Elapsed time: 0.156 seconds; current allocated memory: 256.105 MB." resolution=""/>
	<Message severity="INFO" prefix="[HLS 200-10]" key="HLS_10_1312" tag="" content="Analyzing design file &apos;fast_src/fast_protocol.cpp&apos; ..." resolution=""/>
	<Message severity="INFO" prefix="[HLS 200-10]" key="HLS_10_1312" tag="" content="Analyzing design file &apos;fast_src/fast_encoder.cpp&apos; ..." resolution=""/>
	<Message severity="INFO" prefix="[HLS 200-10]" key="HLS_10_1312" tag="" content="Analyzing design file &apos;fast_src/fast_decoder.cpp&apos; ..." resolution=""/>
	<Message severity="INFO" prefix="[HLS 200-111]" key="HLS_111_966" tag="RUNTIME" content="Finished Source Code Analysis and Preprocessing: CPU user time: 1 seconds. CPU system time: 0 seconds. Elapsed time: 9.551 seconds; current allocated memory: 259.336 MB." resolution=""/>
	<Message severity="INFO" prefix="[HLS 200-777]" key="HLS 200-777" tag="" content="Using interface defaults for &apos;Vivado&apos; flow target." resolution=""/>
	<Message severity="INFO" prefix="[HLS 200-1995]" key="HLS 200-1995" tag="" content="There were 12,161 instructions in the design after the &apos;Compile/Link&apos; phase of compilation. See the Design Size Report for more details: C:/Users/ruuud/spring2025/cse145/AAAAHHHH/ECE1373_2016_hft_on_fpga/src/fast_hls/solution1/syn/report/csynth_design_size.rpt" resolution=""/>
	<Message severity="INFO" prefix="[HLS 200-1995]" key="HLS 200-1995" tag="" content="There were 1,208 instructions in the design after the &apos;Unroll/Inline (step 1)&apos; phase of compilation. See the Design Size Report for more details: C:/Users/ruuud/spring2025/cse145/AAAAHHHH/ECE1373_2016_hft_on_fpga/src/fast_hls/solution1/syn/report/csynth_design_size.rpt" resolution=""/>
	<Message severity="INFO" prefix="[HLS 200-1995]" key="HLS 200-1995" tag="" content="There were 737 instructions in the design after the &apos;Unroll/Inline (step 2)&apos; phase of compilation. See the Design Size Report for more details: C:/Users/ruuud/spring2025/cse145/AAAAHHHH/ECE1373_2016_hft_on_fpga/src/fast_hls/solution1/syn/report/csynth_design_size.rpt" resolution=""/>
	<Message severity="INFO" prefix="[HLS 200-1995]" key="HLS 200-1995" tag="" content="There were 718 instructions in the design after the &apos;Unroll/Inline (step 3)&apos; phase of compilation. See the Design Size Report for more details: C:/Users/ruuud/spring2025/cse145/AAAAHHHH/ECE1373_2016_hft_on_fpga/src/fast_hls/solution1/syn/report/csynth_design_size.rpt" resolution=""/>
	<Message severity="INFO" prefix="[HLS 200-1995]" key="HLS 200-1995" tag="" content="There were 715 instructions in the design after the &apos;Unroll/Inline (step 4)&apos; phase of compilation. See the Design Size Report for more details: C:/Users/ruuud/spring2025/cse145/AAAAHHHH/ECE1373_2016_hft_on_fpga/src/fast_hls/solution1/syn/report/csynth_design_size.rpt" resolution=""/>
	<Message severity="INFO" prefix="[HLS 200-1995]" key="HLS 200-1995" tag="" content="There were 1,272 instructions in the design after the &apos;Array/Struct (step 1)&apos; phase of compilation. See the Design Size Report for more details: C:/Users/ruuud/spring2025/cse145/AAAAHHHH/ECE1373_2016_hft_on_fpga/src/fast_hls/solution1/syn/report/csynth_design_size.rpt" resolution=""/>
	<Message severity="INFO" prefix="[HLS 200-1995]" key="HLS 200-1995" tag="" content="There were 590 instructions in the design after the &apos;Array/Struct (step 2)&apos; phase of compilation. See the Design Size Report for more details: C:/Users/ruuud/spring2025/cse145/AAAAHHHH/ECE1373_2016_hft_on_fpga/src/fast_hls/solution1/syn/report/csynth_design_size.rpt" resolution=""/>
	<Message severity="INFO" prefix="[HLS 200-1995]" key="HLS 200-1995" tag="" content="There were 590 instructions in the design after the &apos;Array/Struct (step 3)&apos; phase of compilation. See the Design Size Report for more details: C:/Users/ruuud/spring2025/cse145/AAAAHHHH/ECE1373_2016_hft_on_fpga/src/fast_hls/solution1/syn/report/csynth_design_size.rpt" resolution=""/>
	<Message severity="INFO" prefix="[HLS 200-1995]" key="HLS 200-1995" tag="" content="There were 694 instructions in the design after the &apos;Array/Struct (step 4)&apos; phase of compilation. See the Design Size Report for more details: C:/Users/ruuud/spring2025/cse145/AAAAHHHH/ECE1373_2016_hft_on_fpga/src/fast_hls/solution1/syn/report/csynth_design_size.rpt" resolution=""/>
	<Message severity="INFO" prefix="[HLS 200-1995]" key="HLS 200-1995" tag="" content="There were 689 instructions in the design after the &apos;Array/Struct (step 5)&apos; phase of compilation. See the Design Size Report for more details: C:/Users/ruuud/spring2025/cse145/AAAAHHHH/ECE1373_2016_hft_on_fpga/src/fast_hls/solution1/syn/report/csynth_design_size.rpt" resolution=""/>
	<Message severity="INFO" prefix="[HLS 200-1995]" key="HLS 200-1995" tag="" content="There were 687 instructions in the design after the &apos;Performance (step 1)&apos; phase of compilation. See the Design Size Report for more details: C:/Users/ruuud/spring2025/cse145/AAAAHHHH/ECE1373_2016_hft_on_fpga/src/fast_hls/solution1/syn/report/csynth_design_size.rpt" resolution=""/>
	<Message severity="INFO" prefix="[HLS 200-1995]" key="HLS 200-1995" tag="" content="There were 686 instructions in the design after the &apos;Performance (step 2)&apos; phase of compilation. See the Design Size Report for more details: C:/Users/ruuud/spring2025/cse145/AAAAHHHH/ECE1373_2016_hft_on_fpga/src/fast_hls/solution1/syn/report/csynth_design_size.rpt" resolution=""/>
	<Message severity="INFO" prefix="[HLS 200-1995]" key="HLS 200-1995" tag="" content="There were 686 instructions in the design after the &apos;Performance (step 3)&apos; phase of compilation. See the Design Size Report for more details: C:/Users/ruuud/spring2025/cse145/AAAAHHHH/ECE1373_2016_hft_on_fpga/src/fast_hls/solution1/syn/report/csynth_design_size.rpt" resolution=""/>
	<Message severity="INFO" prefix="[HLS 200-1995]" key="HLS 200-1995" tag="" content="There were 686 instructions in the design after the &apos;Performance (step 4)&apos; phase of compilation. See the Design Size Report for more details: C:/Users/ruuud/spring2025/cse145/AAAAHHHH/ECE1373_2016_hft_on_fpga/src/fast_hls/solution1/syn/report/csynth_design_size.rpt" resolution=""/>
	<Message severity="INFO" prefix="[HLS 200-1995]" key="HLS 200-1995" tag="" content="There were 677 instructions in the design after the &apos;HW Transforms (step 1)&apos; phase of compilation. See the Design Size Report for more details: C:/Users/ruuud/spring2025/cse145/AAAAHHHH/ECE1373_2016_hft_on_fpga/src/fast_hls/solution1/syn/report/csynth_design_size.rpt" resolution=""/>
	<Message severity="INFO" prefix="[HLS 200-1995]" key="HLS 200-1995" tag="" content="There were 699 instructions in the design after the &apos;HW Transforms (step 2)&apos; phase of compilation. See the Design Size Report for more details: C:/Users/ruuud/spring2025/cse145/AAAAHHHH/ECE1373_2016_hft_on_fpga/src/fast_hls/solution1/syn/report/csynth_design_size.rpt" resolution=""/>
	<Message severity="INFO" prefix="[HLS 214-291]" key="HLS 214-291" tag="" content="Loop &apos;VITIS_LOOP_429_2&apos; is marked as complete unroll implied by the pipeline pragma (fast_src/fast_protocol.cpp:429:31)" resolution=""/>
	<Message severity="INFO" prefix="[HLS 214-291]" key="HLS 214-291" tag="" content="Loop &apos;VITIS_LOOP_409_1&apos; is marked as complete unroll implied by the pipeline pragma (fast_src/fast_protocol.cpp:409:31)" resolution=""/>
	<Message severity="INFO" prefix="[HLS 214-291]" key="HLS 214-291" tag="" content="Loop &apos;anonymous&apos; is marked as complete unroll implied by the pipeline pragma (fast_src/fast_protocol.cpp:391:46)" resolution=""/>
	<Message severity="INFO" prefix="[HLS 214-291]" key="HLS 214-291" tag="" content="Loop &apos;anonymous&apos; is marked as complete unroll implied by the pipeline pragma" resolution=""/>
	<Message severity="INFO" prefix="[HLS 214-291]" key="HLS 214-291" tag="" content="Loop &apos;VITIS_LOOP_192_2&apos; is marked as complete unroll implied by the pipeline pragma (fast_src/fast_protocol.cpp:192:31)" resolution=""/>
	<Message severity="INFO" prefix="[HLS 214-291]" key="HLS 214-291" tag="" content="Loop &apos;VITIS_LOOP_119_1&apos; is marked as complete unroll implied by the pipeline pragma (fast_src/fast_protocol.cpp:119:20)" resolution=""/>
	<Message severity="INFO" prefix="[HLS 214-291]" key="HLS 214-291" tag="" content="Loop &apos;anonymous&apos; is marked as complete unroll implied by the pipeline pragma (fast_src/fast_protocol.cpp:116:41)" resolution=""/>
	<Message severity="INFO" prefix="[HLS 214-291]" key="HLS 214-291" tag="" content="Loop &apos;VITIS_LOOP_310_4&apos; is marked as complete unroll implied by the pipeline pragma (fast_src/fast_protocol.cpp:310:31)" resolution=""/>
	<Message severity="INFO" prefix="[HLS 214-291]" key="HLS 214-291" tag="" content="Loop &apos;VITIS_LOOP_242_3&apos; is marked as complete unroll implied by the pipeline pragma (fast_src/fast_protocol.cpp:242:20)" resolution=""/>
	<Message severity="INFO" prefix="[HLS 214-291]" key="HLS 214-291" tag="" content="Loop &apos;anonymous&apos; is marked as complete unroll implied by the pipeline pragma (fast_src/fast_protocol.cpp:239:41)" resolution=""/>
	<Message severity="INFO" prefix="[HLS 214-186]" key="HLS 214-186" tag="" content="Unrolling loop &apos;VITIS_LOOP_429_2&apos; (fast_src/fast_protocol.cpp:429:31) in function &apos;txPath&apos; completely with a factor of 8 (fast_src/fast_protocol.cpp:354:0)" resolution=""/>
	<Message severity="INFO" prefix="[HLS 214-186]" key="HLS 214-186" tag="" content="Unrolling loop &apos;VITIS_LOOP_409_1&apos; (fast_src/fast_protocol.cpp:409:31) in function &apos;txPath&apos; completely with a factor of 4 (fast_src/fast_protocol.cpp:354:0)" resolution=""/>
	<Message severity="INFO" prefix="[HLS 214-186]" key="HLS 214-186" tag="" content="Unrolling loop &apos;anonymous&apos; (fast_src/fast_protocol.cpp:391:46) in function &apos;txPath&apos; completely with a factor of 15 (fast_src/fast_protocol.cpp:354:0)" resolution=""/>
	<Message severity="INFO" prefix="[HLS 214-186]" key="HLS 214-186" tag="" content="Unrolling loop &apos;anonymous&apos; () in function &apos;txPath&apos; completely with a factor of 1 (fast_src/fast_protocol.cpp:354:0)" resolution=""/>
	<Message severity="INFO" prefix="[HLS 214-186]" key="HLS 214-186" tag="" content="Unrolling loop &apos;VITIS_LOOP_192_2&apos; (fast_src/fast_protocol.cpp:192:31) in function &apos;rxPath&apos; completely with a factor of 4 (fast_src/fast_protocol.cpp:37:0)" resolution=""/>
	<Message severity="INFO" prefix="[HLS 214-186]" key="HLS 214-186" tag="" content="Unrolling loop &apos;VITIS_LOOP_119_1&apos; (fast_src/fast_protocol.cpp:119:20) in function &apos;rxPath&apos; completely with a factor of 8 (fast_src/fast_protocol.cpp:37:0)" resolution=""/>
	<Message severity="INFO" prefix="[HLS 214-186]" key="HLS 214-186" tag="" content="Unrolling loop &apos;anonymous&apos; (fast_src/fast_protocol.cpp:116:41) in function &apos;rxPath&apos; completely with a factor of 15 (fast_src/fast_protocol.cpp:37:0)" resolution=""/>
	<Message severity="INFO" prefix="[HLS 214-186]" key="HLS 214-186" tag="" content="Unrolling loop &apos;anonymous&apos; () in function &apos;rxPath&apos; completely with a factor of 1 (fast_src/fast_protocol.cpp:37:0)" resolution=""/>
	<Message severity="INFO" prefix="[HLS 214-186]" key="HLS 214-186" tag="" content="Unrolling loop &apos;VITIS_LOOP_310_4&apos; (fast_src/fast_protocol.cpp:310:31) in function &apos;rxPath&apos; completely with a factor of 4 (fast_src/fast_protocol.cpp:37:0)" resolution=""/>
	<Message severity="INFO" prefix="[HLS 214-186]" key="HLS 214-186" tag="" content="Unrolling loop &apos;VITIS_LOOP_242_3&apos; (fast_src/fast_protocol.cpp:242:20) in function &apos;rxPath&apos; completely with a factor of 8 (fast_src/fast_protocol.cpp:37:0)" resolution=""/>
	<Message severity="INFO" prefix="[HLS 214-186]" key="HLS 214-186" tag="" content="Unrolling loop &apos;anonymous&apos; (fast_src/fast_protocol.cpp:239:41) in function &apos;rxPath&apos; completely with a factor of 15 (fast_src/fast_protocol.cpp:37:0)" resolution=""/>
	<Message severity="INFO" prefix="[HLS 214-178]" key="HLS 214-178" tag="" content="Inlining function &apos;ap_uint&lt;8&gt;::ap_uint(double)&apos; into &apos;rxPath(hls::stream&lt;axiWord, 0&gt;&amp;, hls::stream&lt;metadata, 0&gt;&amp;, hls::stream&lt;ap_uint&lt;16&gt;, 0&gt;&amp;, hls::stream&lt;bool, 0&gt;&amp;, hls::stream&lt;metadata, 0&gt;&amp;, hls::stream&lt;ap_uint&lt;64&gt;, 0&gt;&amp;, hls::stream&lt;ap_uint&lt;64&gt;, 0&gt;&amp;, hls::stream&lt;order, 0&gt;&amp;)&apos; (fast_src/fast_protocol.cpp:37:0)" resolution=""/>
	<Message severity="INFO" prefix="[HLS 214-178]" key="HLS 214-178" tag="" content="Inlining function &apos;ap_uint&lt;8&gt;::ap_uint(double)&apos; into &apos;txPath(hls::stream&lt;metadata, 0&gt;&amp;, hls::stream&lt;axiWord, 0&gt;&amp;, hls::stream&lt;metadata, 0&gt;&amp;, hls::stream&lt;ap_uint&lt;16&gt;, 0&gt;&amp;, hls::stream&lt;ap_uint&lt;64&gt;, 0&gt;&amp;, hls::stream&lt;ap_uint&lt;64&gt;, 0&gt;&amp;, hls::stream&lt;order, 0&gt;&amp;)&apos; (fast_src/fast_protocol.cpp:354:0)" resolution=""/>
	<Message severity="INFO" prefix="[HLS 214-248]" key="HLS 214-248" tag="" content="Applying array_partition to &apos;encoded_message&apos;: Complete partitioning on dimension 1. (fast_src/fast_protocol.cpp:116:19)" resolution=""/>
	<Message severity="INFO" prefix="[HLS 214-248]" key="HLS 214-248" tag="" content="Applying array_partition to &apos;encoded_message149&apos;: Complete partitioning on dimension 1. (fast_src/fast_protocol.cpp:239:19)" resolution=""/>
	<Message severity="INFO" prefix="[HLS 214-248]" key="HLS 214-248" tag="" content="Applying array_partition to &apos;encoded_message&apos;: Complete partitioning on dimension 1. (fast_src/fast_protocol.cpp:391:24)" resolution=""/>
	<Message severity="INFO" prefix="[HLS 214-241]" key="HLS 214-241" tag="" content="Aggregating axis (hls::stream) variable &apos;lbRxMetadataIn&apos; with compact=bit mode in 96-bits (fast_src/fast_protocol.cpp:516:0)" resolution=""/>
	<Message severity="INFO" prefix="[HLS 214-241]" key="HLS 214-241" tag="" content="Aggregating axis (hls::stream) variable &apos;lbTxMetadataOut&apos; with compact=bit mode in 96-bits (fast_src/fast_protocol.cpp:516:0)" resolution=""/>
	<Message severity="INFO" prefix="[HLS 214-241]" key="HLS 214-241" tag="" content="Aggregating axis (hls::stream) variable &apos;order_to_book&apos; with compact=bit mode in 64-bits (fast_src/fast_protocol.cpp:516:0)" resolution=""/>
	<Message severity="INFO" prefix="[HLS 214-241]" key="HLS 214-241" tag="" content="Aggregating axis (hls::stream) variable &apos;order_from_book&apos; with compact=bit mode in 64-bits (fast_src/fast_protocol.cpp:516:0)" resolution=""/>
	<Message severity="INFO" prefix="[HLS 200-111]" key="HLS_111_966" tag="RUNTIME" content="Finished Compiling Optimization and Transform: CPU user time: 0 seconds. CPU system time: 0 seconds. Elapsed time: 7.819 seconds; current allocated memory: 261.574 MB." resolution=""/>
	<Message severity="INFO" prefix="[HLS 200-111]" key="HLS_111_966" tag="RUNTIME" content="Finished Checking Pragmas: CPU user time: 0 seconds. CPU system time: 0 seconds. Elapsed time: 0.008 seconds; current allocated memory: 261.574 MB." resolution=""/>
	<Message severity="INFO" prefix="[HLS 200-10]" key="HLS_10_1467" tag="" content="Starting code transformations ..." resolution=""/>
	<Message severity="INFO" prefix="[HLS 200-111]" key="HLS_111_966" tag="RUNTIME" content="Finished Standard Transforms: CPU user time: 0 seconds. CPU system time: 0 seconds. Elapsed time: 0.074 seconds; current allocated memory: 267.059 MB." resolution=""/>
	<Message severity="INFO" prefix="[HLS 200-10]" key="HLS_10_1472" tag="" content="Checking synthesizability ..." resolution=""/>
	<Message severity="INFO" prefix="[HLS 200-111]" key="HLS_111_966" tag="RUNTIME" content="Finished Checking Synthesizability: CPU user time: 0 seconds. CPU system time: 0 seconds. Elapsed time: 0.078 seconds; current allocated memory: 269.840 MB." resolution=""/>
	<Message severity="INFO" prefix="[XFORM 203-712]" key="XFORM_DATAFLOW_TRANSFORM_230" tag="DATAFLOW" content="Applying dataflow to function &apos;fast_protocol&apos; (fast_src/fast_protocol.cpp:501:1), detected/extracted 2 process function(s): 
	 &apos;rxPath&apos;
	 &apos;txPath&apos;." resolution=""/>
	<Message severity="INFO" prefix="[XFORM 203-401]" key="XFORM_IFCONV_STATUS_239" tag="" content="Performing if-conversion on hyperblock from (fast_src/fast_protocol.cpp:376:42) to (fast_src/fast_protocol.cpp:450:9) in function &apos;txPath&apos;... converting 25 basic blocks." resolution=""/>
	<Message severity="INFO" prefix="[XFORM 203-401]" key="XFORM_IFCONV_STATUS_239" tag="" content="Performing if-conversion on hyperblock from (fast_src/fast_protocol.cpp:122:45) to (fast_src/fast_protocol.cpp:218:9) in function &apos;rxPath&apos;... converting 8 basic blocks." resolution=""/>
	<Message severity="INFO" prefix="[XFORM 203-401]" key="XFORM_IFCONV_STATUS_239" tag="" content="Performing if-conversion on hyperblock from (fast_src/fast_protocol.cpp:245:45) to (fast_src/fast_protocol.cpp:336:9) in function &apos;rxPath&apos;... converting 8 basic blocks." resolution=""/>
	<Message severity="INFO" prefix="[XFORM 203-11]" key="XFORM_EXPR_BALANCE_STATUS_178" tag="" content="Balancing expressions in function &apos;txPath&apos; (fast_src/fast_protocol.cpp:347:9)...11 expression(s) balanced." resolution=""/>
	<Message severity="INFO" prefix="[HLS 200-111]" key="HLS_111_966" tag="RUNTIME" content="Finished Loop, function and other optimizations: CPU user time: 1 seconds. CPU system time: 0 seconds. Elapsed time: 0.253 seconds; current allocated memory: 292.812 MB." resolution=""/>
	<Message severity="INFO" prefix="[HLS 200-111]" key="HLS_111_966" tag="RUNTIME" content="Finished Architecture Synthesis: CPU user time: 0 seconds. CPU system time: 0 seconds. Elapsed time: 0.215 seconds; current allocated memory: 304.637 MB." resolution=""/>
	<Message severity="INFO" prefix="[HLS 200-10]" key="HLS_10_1317" tag="" content="Starting hardware synthesis ..." resolution=""/>
	<Message severity="INFO" prefix="[HLS 200-10]" key="HLS_10_1385" tag="" content="Synthesizing &apos;fast_protocol&apos; ..." resolution=""/>
	<Message severity="INFO" prefix="[HLS 200-10]" key="HLS_10_1477" tag="" content="----------------------------------------------------------------" resolution=""/>
	<Message severity="INFO" prefix="[HLS 200-42]" key="HLS_42_1438" tag="" content="-- Implementing module &apos;rxPath&apos;" resolution=""/>
	<Message severity="INFO" prefix="[HLS 200-10]" key="HLS_10_1478" tag="" content="----------------------------------------------------------------" resolution=""/>
	<Message severity="INFO" prefix="[SCHED 204-11]" key="SCHED_SCHED_STATUS_597" tag="" content="Starting scheduling ..." resolution=""/>
	<Message severity="INFO" prefix="[SCHED 204-61]" key="SCHED_PIPELINING_STATUS_46" tag="" content="Pipelining function &apos;rxPath&apos;." resolution=""/>
	<Message severity="WARNING" prefix="[HLS 200-880]" key="HLS 200-880" tag="LOOP,SCHEDULE,VITIS_THROUGHPUT" content="The II Violation in module &apos;rxPath&apos; (function &apos;rxPath&apos;): Unable to enforce a carried dependence constraint (II = 1, distance = 1, offset = 0) between &apos;store&apos; operation 0 bit (&apos;next_state_1_write_ln100&apos;, fast_src/fast_protocol.cpp:100) of variable &apos;select_ln100&apos;, fast_src/fast_protocol.cpp:100 on static variable &apos;next_state_1&apos; and &apos;load&apos; operation 3 bit (&apos;next_state_1_load&apos;, fast_src/fast_protocol.cpp:56) on static variable &apos;next_state_1&apos;." resolution="http://docs.xilinx.com/access/sources/dita/topic?Doc_Version=2024.2%20English&amp;url=ug1448-hls-guidance&amp;resourceid=200-880.html"/>
	<Message severity="WARNING" prefix="[HLS 200-880]" key="HLS 200-880" tag="LOOP,SCHEDULE,VITIS_THROUGHPUT" content="The II Violation in module &apos;rxPath&apos; (function &apos;rxPath&apos;): Unable to enforce a carried dependence constraint (II = 2, distance = 1, offset = 1) between axis read operation (&apos;lbRxDataIn_read_1&apos;, fast_src/fast_protocol.cpp:96) on port &apos;lbRxDataIn&apos; (fast_src/fast_protocol.cpp:96) and axis request operation (&apos;tmp_12&apos;, fast_src/fast_protocol.cpp:78) on port &apos;lbRxDataIn&apos; (fast_src/fast_protocol.cpp:78)." resolution="http://docs.xilinx.com/access/sources/dita/topic?Doc_Version=2024.2%20English&amp;url=ug1448-hls-guidance&amp;resourceid=200-880.html"/>
	<Message severity="INFO" prefix="[HLS 200-1470]" key="HLS 200-1470" tag="SCHEDULE,VITIS_THROUGHPUT" content="Pipelining result : Target II = 1, Final II = 3, Depth = 5, function &apos;rxPath&apos;" resolution=""/>
	<Message severity="INFO" prefix="[SCHED 204-11]" key="SCHED_SCHED_STATUS_596" tag="" content="Finished scheduling." resolution=""/>
	<Message severity="INFO" prefix="[HLS 200-111]" key="HLS_111_966" tag="RUNTIME" content="Finished Scheduling: CPU user time: 0 seconds. CPU system time: 0 seconds. Elapsed time: 0.299 seconds; current allocated memory: 311.012 MB." resolution=""/>
	<Message severity="INFO" prefix="[BIND 205-100]" key="BIND_100_926" tag="" content="Starting micro-architecture generation ..." resolution=""/>
	<Message severity="INFO" prefix="[BIND 205-101]" key="BIND_101_698" tag="" content="Performing variable lifetime analysis." resolution=""/>
	<Message severity="INFO" prefix="[BIND 205-101]" key="BIND_101_697" tag="" content="Exploring resource sharing." resolution=""/>
	<Message severity="INFO" prefix="[BIND 205-101]" key="BIND_101_693" tag="" content="Binding ..." resolution=""/>
	<Message severity="INFO" prefix="[BIND 205-100]" key="BIND_100_925" tag="" content="Finished micro-architecture generation." resolution=""/>
	<Message severity="INFO" prefix="[HLS 200-111]" key="HLS_111_966" tag="RUNTIME" content="Finished Binding: CPU user time: 0 seconds. CPU system time: 0 seconds. Elapsed time: 0.151 seconds; current allocated memory: 312.641 MB." resolution=""/>
	<Message severity="INFO" prefix="[HLS 200-10]" key="HLS_10_1477" tag="" content="----------------------------------------------------------------" resolution=""/>
	<Message severity="INFO" prefix="[HLS 200-42]" key="HLS_42_1438" tag="" content="-- Implementing module &apos;txPath&apos;" resolution=""/>
	<Message severity="INFO" prefix="[HLS 200-10]" key="HLS_10_1478" tag="" content="----------------------------------------------------------------" resolution=""/>
	<Message severity="INFO" prefix="[SCHED 204-11]" key="SCHED_SCHED_STATUS_597" tag="" content="Starting scheduling ..." resolution=""/>
	<Message severity="INFO" prefix="[SCHED 204-61]" key="SCHED_PIPELINING_STATUS_46" tag="" content="Pipelining function &apos;txPath&apos;." resolution=""/>
	<Message severity="WARNING" prefix="[HLS 200-880]" key="HLS 200-880" tag="LOOP,SCHEDULE,VITIS_THROUGHPUT" content="The II Violation in module &apos;txPath&apos; (function &apos;txPath&apos;): Unable to enforce a carried dependence constraint (II = 1, distance = 1, offset = 0) between &apos;store&apos; operation 0 bit (&apos;next_state_write_ln495&apos;, fast_src/fast_protocol.cpp:495) of constant 0 on static variable &apos;next_state&apos; and &apos;load&apos; operation 2 bit (&apos;next_state_load&apos;, fast_src/fast_protocol.cpp:367) on static variable &apos;next_state&apos;." resolution="http://docs.xilinx.com/access/sources/dita/topic?Doc_Version=2024.2%20English&amp;url=ug1448-hls-guidance&amp;resourceid=200-880.html"/>
	<Message severity="WARNING" prefix="[HLS 200-880]" key="HLS 200-880" tag="LOOP,SCHEDULE,VITIS_THROUGHPUT" content="The II Violation in module &apos;txPath&apos; (function &apos;txPath&apos;): Unable to enforce a carried dependence constraint (II = 2, distance = 1, offset = 0) between &apos;store&apos; operation 0 bit (&apos;next_state_write_ln448&apos;, fast_src/fast_protocol.cpp:448) of constant 1 on static variable &apos;next_state&apos; and &apos;load&apos; operation 2 bit (&apos;next_state_load&apos;, fast_src/fast_protocol.cpp:367) on static variable &apos;next_state&apos;." resolution="http://docs.xilinx.com/access/sources/dita/topic?Doc_Version=2024.2%20English&amp;url=ug1448-hls-guidance&amp;resourceid=200-880.html"/>
	<Message severity="WARNING" prefix="[HLS 200-880]" key="HLS 200-880" tag="LOOP,SCHEDULE,VITIS_THROUGHPUT" content="The II Violation in module &apos;txPath&apos; (function &apos;txPath&apos;): Unable to enforce a carried dependence constraint (II = 3, distance = 1, offset = 1) between axis read operation (&apos;metadata_from_book_read&apos;, fast_src/fast_protocol.cpp:377) on port &apos;metadata_from_book&apos; (fast_src/fast_protocol.cpp:377) and axis request operation (&apos;tmp&apos;, fast_src/fast_protocol.cpp:371) on port &apos;metadata_from_book&apos; (fast_src/fast_protocol.cpp:371)." resolution="http://docs.xilinx.com/access/sources/dita/topic?Doc_Version=2024.2%20English&amp;url=ug1448-hls-guidance&amp;resourceid=200-880.html"/>
	<Message severity="INFO" prefix="[HLS 200-1470]" key="HLS 200-1470" tag="SCHEDULE,VITIS_THROUGHPUT" content="Pipelining result : Target II = 1, Final II = 4, Depth = 6, function &apos;txPath&apos;" resolution=""/>
	<Message severity="INFO" prefix="[SCHED 204-11]" key="SCHED_SCHED_STATUS_596" tag="" content="Finished scheduling." resolution=""/>
	<Message severity="INFO" prefix="[HLS 200-111]" key="HLS_111_966" tag="RUNTIME" content="Finished Scheduling: CPU user time: 0 seconds. CPU system time: 0 seconds. Elapsed time: 0.257 seconds; current allocated memory: 314.219 MB." resolution=""/>
	<Message severity="INFO" prefix="[BIND 205-100]" key="BIND_100_926" tag="" content="Starting micro-architecture generation ..." resolution=""/>
	<Message severity="INFO" prefix="[BIND 205-101]" key="BIND_101_698" tag="" content="Performing variable lifetime analysis." resolution=""/>
	<Message severity="INFO" prefix="[BIND 205-101]" key="BIND_101_697" tag="" content="Exploring resource sharing." resolution=""/>
	<Message severity="INFO" prefix="[BIND 205-101]" key="BIND_101_693" tag="" content="Binding ..." resolution=""/>
	<Message severity="INFO" prefix="[BIND 205-100]" key="BIND_100_925" tag="" content="Finished micro-architecture generation." resolution=""/>
	<Message severity="INFO" prefix="[HLS 200-111]" key="HLS_111_966" tag="RUNTIME" content="Finished Binding: CPU user time: 0 seconds. CPU system time: 0 seconds. Elapsed time: 0.099 seconds; current allocated memory: 314.727 MB." resolution=""/>
	<Message severity="INFO" prefix="[HLS 200-10]" key="HLS_10_1477" tag="" content="----------------------------------------------------------------" resolution=""/>
	<Message severity="INFO" prefix="[HLS 200-42]" key="HLS_42_1438" tag="" content="-- Implementing module &apos;fast_protocol&apos;" resolution=""/>
	<Message severity="INFO" prefix="[HLS 200-10]" key="HLS_10_1478" tag="" content="----------------------------------------------------------------" resolution=""/>
	<Message severity="INFO" prefix="[SCHED 204-11]" key="SCHED_SCHED_STATUS_597" tag="" content="Starting scheduling ..." resolution=""/>
	<Message severity="INFO" prefix="[SCHED 204-11]" key="SCHED_SCHED_STATUS_596" tag="" content="Finished scheduling." resolution=""/>
	<Message severity="INFO" prefix="[HLS 200-111]" key="HLS_111_966" tag="RUNTIME" content="Finished Scheduling: CPU user time: 0 seconds. CPU system time: 0 seconds. Elapsed time: 0.114 seconds; current allocated memory: 314.883 MB." resolution=""/>
	<Message severity="INFO" prefix="[BIND 205-100]" key="BIND_100_926" tag="" content="Starting micro-architecture generation ..." resolution=""/>
	<Message severity="INFO" prefix="[BIND 205-101]" key="BIND_101_698" tag="" content="Performing variable lifetime analysis." resolution=""/>
	<Message severity="INFO" prefix="[BIND 205-101]" key="BIND_101_697" tag="" content="Exploring resource sharing." resolution=""/>
	<Message severity="INFO" prefix="[BIND 205-101]" key="BIND_101_693" tag="" content="Binding ..." resolution=""/>
	<Message severity="INFO" prefix="[BIND 205-100]" key="BIND_100_925" tag="" content="Finished micro-architecture generation." resolution=""/>
	<Message severity="INFO" prefix="[HLS 200-111]" key="HLS_111_966" tag="RUNTIME" content="Finished Binding: CPU user time: 0 seconds. CPU system time: 0 seconds. Elapsed time: 0.071 seconds; current allocated memory: 315.086 MB." resolution=""/>
	<Message severity="INFO" prefix="[HLS 200-10]" key="HLS_10_1483" tag="" content="----------------------------------------------------------------" resolution=""/>
	<Message severity="INFO" prefix="[HLS 200-10]" key="HLS_10_1484" tag="" content="-- Generating RTL for module &apos;rxPath&apos;" resolution=""/>
	<Message severity="INFO" prefix="[HLS 200-10]" key="HLS_10_1485" tag="" content="----------------------------------------------------------------" resolution=""/>
	<Message severity="WARNING" prefix="[RTGEN 206-101]" key="RTGEN_101_861" tag="" content="Register &apos;next_state_1&apos; is power-on initialization." resolution=""/>
	<Message severity="WARNING" prefix="[RTGEN 206-101]" key="RTGEN_101_861" tag="" content="Register &apos;first_packet&apos; is power-on initialization." resolution=""/>
	<Message severity="WARNING" prefix="[RTGEN 206-101]" key="RTGEN_101_861" tag="" content="Register &apos;second_packet&apos; is power-on initialization." resolution=""/>
	<Message severity="WARNING" prefix="[RTGEN 206-101]" key="RTGEN_101_861" tag="" content="Register &apos;openPortWaitTime&apos; is power-on initialization." resolution=""/>
	<Message severity="WARNING" prefix="[RTGEN 206-101]" key="RTGEN_101_861" tag="" content="Register &apos;temp_order_price&apos; is power-on initialization." resolution=""/>
	<Message severity="WARNING" prefix="[RTGEN 206-101]" key="RTGEN_101_861" tag="" content="Register &apos;temp_order_size&apos; is power-on initialization." resolution=""/>
	<Message severity="WARNING" prefix="[RTGEN 206-101]" key="RTGEN_101_861" tag="" content="Register &apos;temp_order_orderID&apos; is power-on initialization." resolution=""/>
	<Message severity="WARNING" prefix="[RTGEN 206-101]" key="RTGEN_101_861" tag="" content="Register &apos;temp_order_type&apos; is power-on initialization." resolution=""/>
	<Message severity="INFO" prefix="[RTGEN 206-100]" key="RTGEN_100_855" tag="" content="Generating core module &apos;mul_16s_9ns_16_1_1&apos;: 2 instance(s)." resolution=""/>
	<Message severity="INFO" prefix="[RTGEN 206-100]" key="RTGEN_100_855" tag="" content="Generating core module &apos;sparsemux_11_4_25_1_1&apos;: 2 instance(s)." resolution=""/>
	<Message severity="INFO" prefix="[RTGEN 206-100]" key="RTGEN_100_855" tag="" content="Generating core module &apos;sparsemux_11_4_4_1_1&apos;: 2 instance(s)." resolution=""/>
	<Message severity="INFO" prefix="[RTGEN 206-100]" key="RTGEN_100_855" tag="" content="Generating core module &apos;sparsemux_17_4_3_1_1&apos;: 2 instance(s)." resolution=""/>
	<Message severity="INFO" prefix="[RTGEN 206-100]" key="RTGEN_100_855" tag="" content="Generating core module &apos;sparsemux_17_4_7_1_1&apos;: 2 instance(s)." resolution=""/>
	<Message severity="INFO" prefix="[RTGEN 206-100]" key="RTGEN_100_855" tag="" content="Generating core module &apos;sparsemux_7_3_7_1_1&apos;: 2 instance(s)." resolution=""/>
	<Message severity="INFO" prefix="[RTGEN 206-100]" key="RTGEN_100_855" tag="" content="Generating core module &apos;sparsemux_7_3_8_1_1&apos;: 2 instance(s)." resolution=""/>
	<Message severity="INFO" prefix="[RTGEN 206-100]" key="RTGEN_100_855" tag="" content="Generating core module &apos;sparsemux_9_3_7_1_1&apos;: 2 instance(s)." resolution=""/>
	<Message severity="INFO" prefix="[RTGEN 206-100]" key="RTGEN_100_855" tag="" content="Generating core module &apos;sparsemux_9_3_8_1_1&apos;: 8 instance(s)." resolution=""/>
	<Message severity="INFO" prefix="[RTGEN 206-100]" key="RTGEN_100_856" tag="" content="Finished creating RTL model for &apos;rxPath&apos;." resolution=""/>
	<Message severity="INFO" prefix="[RTMG 210-279]" key="RTMG_279_1793" tag="" content="Implementing memory &apos;fast_protocol_rxPath_POW10_ROM_AUTO_1R&apos; using auto ROMs." resolution=""/>
	<Message severity="INFO" prefix="[HLS 200-111]" key="HLS_111_966" tag="RUNTIME" content="Finished Creating RTL model: CPU user time: 0 seconds. CPU system time: 0 seconds. Elapsed time: 0.389 seconds; current allocated memory: 320.508 MB." resolution=""/>
	<Message severity="INFO" prefix="[HLS 200-10]" key="HLS_10_1483" tag="" content="----------------------------------------------------------------" resolution=""/>
	<Message severity="INFO" prefix="[HLS 200-10]" key="HLS_10_1484" tag="" content="-- Generating RTL for module &apos;txPath&apos;" resolution=""/>
	<Message severity="INFO" prefix="[HLS 200-10]" key="HLS_10_1485" tag="" content="----------------------------------------------------------------" resolution=""/>
	<Message severity="WARNING" prefix="[RTGEN 206-101]" key="RTGEN_101_861" tag="" content="Register &apos;next_state&apos; is power-on initialization." resolution=""/>
	<Message severity="WARNING" prefix="[RTGEN 206-101]" key="RTGEN_101_861" tag="" content="Register &apos;first_packet_data&apos; is power-on initialization." resolution=""/>
	<Message severity="WARNING" prefix="[RTGEN 206-101]" key="RTGEN_101_861" tag="" content="Register &apos;second_packet_data&apos; is power-on initialization." resolution=""/>
	<Message severity="WARNING" prefix="[RTGEN 206-101]" key="RTGEN_101_861" tag="" content="Register &apos;lbPacketLength&apos; is power-on initialization." resolution=""/>
	<Message severity="WARNING" prefix="[RTGEN 206-101]" key="RTGEN_101_751" tag="" content="RTL name &apos;sparsemux_11_4_4_1_1&apos; is changed to &apos;sparsemux_11_4_4_1_1_x&apos; due to conflict." resolution=""/>
	<Message severity="INFO" prefix="[RTGEN 206-100]" key="RTGEN_100_855" tag="" content="Generating core module &apos;sparsemux_11_32_8_1_1&apos;: 5 instance(s)." resolution=""/>
	<Message severity="INFO" prefix="[RTGEN 206-100]" key="RTGEN_100_855" tag="" content="Generating core module &apos;sparsemux_11_4_4_1_1_x&apos;: 1 instance(s)." resolution=""/>
	<Message severity="INFO" prefix="[RTGEN 206-100]" key="RTGEN_100_855" tag="" content="Generating core module &apos;sparsemux_13_5_4_1_1&apos;: 1 instance(s)." resolution=""/>
	<Message severity="INFO" prefix="[RTGEN 206-100]" key="RTGEN_100_855" tag="" content="Generating core module &apos;sparsemux_9_3_4_1_1&apos;: 1 instance(s)." resolution=""/>
	<Message severity="INFO" prefix="[RTGEN 206-100]" key="RTGEN_100_856" tag="" content="Finished creating RTL model for &apos;txPath&apos;." resolution=""/>
	<Message severity="INFO" prefix="[HLS 200-111]" key="HLS_111_966" tag="RUNTIME" content="Finished Creating RTL model: CPU user time: 1 seconds. CPU system time: 1 seconds. Elapsed time: 0.794 seconds; current allocated memory: 327.793 MB." resolution=""/>
	<Message severity="INFO" prefix="[HLS 200-10]" key="HLS_10_1483" tag="" content="----------------------------------------------------------------" resolution=""/>
	<Message severity="INFO" prefix="[HLS 200-10]" key="HLS_10_1484" tag="" content="-- Generating RTL for module &apos;fast_protocol&apos;" resolution=""/>
	<Message severity="INFO" prefix="[HLS 200-10]" key="HLS_10_1485" tag="" content="----------------------------------------------------------------" resolution=""/>
	<Message severity="WARNING" prefix="[RTGEN 206-101]" key="RTGEN_101_918" tag="" content="Design contains AXI ports. Reset is fixed to synchronous and active low." resolution=""/>
	<Message severity="INFO" prefix="[RTGEN 206-500]" key="PREPROC_IO_COMP_CONFLICT_1950" tag="" content="Setting interface mode on port &apos;fast_protocol/lbRxDataIn&apos; to &apos;axis&apos; (register, both mode)." resolution=""/>
	<Message severity="INFO" prefix="[RTGEN 206-500]" key="PREPROC_IO_COMP_CONFLICT_1950" tag="" content="Setting interface mode on port &apos;fast_protocol/lbRxMetadataIn&apos; to &apos;axis&apos; (register, both mode)." resolution=""/>
	<Message severity="INFO" prefix="[RTGEN 206-500]" key="PREPROC_IO_COMP_CONFLICT_1950" tag="" content="Setting interface mode on port &apos;fast_protocol/lbRequestPortOpenOut&apos; to &apos;axis&apos; (register, both mode)." resolution=""/>
	<Message severity="INFO" prefix="[RTGEN 206-500]" key="PREPROC_IO_COMP_CONFLICT_1950" tag="" content="Setting interface mode on port &apos;fast_protocol/lbPortOpenReplyIn&apos; to &apos;axis&apos; (register, both mode)." resolution=""/>
	<Message severity="INFO" prefix="[RTGEN 206-500]" key="PREPROC_IO_COMP_CONFLICT_1950" tag="" content="Setting interface mode on port &apos;fast_protocol/lbTxDataOut&apos; to &apos;axis&apos; (register, both mode)." resolution=""/>
	<Message severity="INFO" prefix="[RTGEN 206-500]" key="PREPROC_IO_COMP_CONFLICT_1950" tag="" content="Setting interface mode on port &apos;fast_protocol/lbTxMetadataOut&apos; to &apos;axis&apos; (register, both mode)." resolution=""/>
	<Message severity="INFO" prefix="[RTGEN 206-500]" key="PREPROC_IO_COMP_CONFLICT_1950" tag="" content="Setting interface mode on port &apos;fast_protocol/lbTxLengthOut&apos; to &apos;axis&apos; (register, both mode)." resolution=""/>
	<Message severity="INFO" prefix="[RTGEN 206-500]" key="PREPROC_IO_COMP_CONFLICT_1950" tag="" content="Setting interface mode on port &apos;fast_protocol/tagsIn&apos; to &apos;axis&apos; (register, both mode)." resolution=""/>
	<Message severity="INFO" prefix="[RTGEN 206-500]" key="PREPROC_IO_COMP_CONFLICT_1950" tag="" content="Setting interface mode on port &apos;fast_protocol/tagsOut&apos; to &apos;axis&apos; (register, both mode)." resolution=""/>
	<Message severity="INFO" prefix="[RTGEN 206-500]" key="PREPROC_IO_COMP_CONFLICT_1950" tag="" content="Setting interface mode on port &apos;fast_protocol/metadata_to_book&apos; to &apos;axis&apos; (register, both mode)." resolution=""/>
	<Message severity="INFO" prefix="[RTGEN 206-500]" key="PREPROC_IO_COMP_CONFLICT_1950" tag="" content="Setting interface mode on port &apos;fast_protocol/metadata_from_book&apos; to &apos;axis&apos; (register, both mode)." resolution=""/>
	<Message severity="INFO" prefix="[RTGEN 206-500]" key="PREPROC_IO_COMP_CONFLICT_1950" tag="" content="Setting interface mode on port &apos;fast_protocol/time_to_book&apos; to &apos;axis&apos; (register, both mode)." resolution=""/>
	<Message severity="INFO" prefix="[RTGEN 206-500]" key="PREPROC_IO_COMP_CONFLICT_1950" tag="" content="Setting interface mode on port &apos;fast_protocol/time_from_book&apos; to &apos;axis&apos; (register, both mode)." resolution=""/>
	<Message severity="INFO" prefix="[RTGEN 206-500]" key="PREPROC_IO_COMP_CONFLICT_1950" tag="" content="Setting interface mode on port &apos;fast_protocol/order_to_book&apos; to &apos;axis&apos; (register, both mode)." resolution=""/>
	<Message severity="INFO" prefix="[RTGEN 206-500]" key="PREPROC_IO_COMP_CONFLICT_1950" tag="" content="Setting interface mode on port &apos;fast_protocol/order_from_book&apos; to &apos;axis&apos; (register, both mode)." resolution=""/>
	<Message severity="INFO" prefix="[RTGEN 206-500]" key="PREPROC_IO_COMP_CONFLICT_1950" tag="" content="Setting interface mode on function &apos;fast_protocol&apos; to &apos;ap_ctrl_none&apos;." resolution=""/>
	<Message severity="WARNING" prefix="[HLS 200-656]" key="HLS 200-656" tag="AXI,VITIS_INTERFACE" content="Deadlocks can occur since process rxPath is instantiated in a dataflow region with ap_ctrl_none or without start propagation and contains an auto-rewind pipeline." resolution="http://docs.xilinx.com/access/sources/dita/topic?Doc_Version=2024.2%20English&amp;url=ug1448-hls-guidance&amp;resourceid=200-656.html"/>
	<Message severity="WARNING" prefix="[HLS 200-656]" key="HLS 200-656" tag="AXI,VITIS_INTERFACE" content="Deadlocks can occur since process txPath is instantiated in a dataflow region with ap_ctrl_none or without start propagation and contains an auto-rewind pipeline." resolution="http://docs.xilinx.com/access/sources/dita/topic?Doc_Version=2024.2%20English&amp;url=ug1448-hls-guidance&amp;resourceid=200-656.html"/>
	<Message severity="WARNING" prefix="[HLS 200-656]" key="HLS 200-656" tag="AXI,VITIS_INTERFACE" content="Deadlocks can occur since process rxPath is instantiated in a dataflow region with ap_ctrl_none or without start propagation and contains an auto-rewind pipeline." resolution="http://docs.xilinx.com/access/sources/dita/topic?Doc_Version=2024.2%20English&amp;url=ug1448-hls-guidance&amp;resourceid=200-656.html"/>
	<Message severity="INFO" prefix="[HLS 200-633]" key="HLS 200-633" tag="" content="Setting ap_ctrl_none interface for fast_protocol" resolution=""/>
	<Message severity="INFO" prefix="[RTGEN 206-100]" key="RTGEN_100_856" tag="" content="Finished creating RTL model for &apos;fast_protocol&apos;." resolution=""/>
	<Message severity="INFO" prefix="[HLS 200-111]" key="HLS_111_966" tag="RUNTIME" content="Finished Creating RTL model: CPU user time: 0 seconds. CPU system time: 0 seconds. Elapsed time: 0.631 seconds; current allocated memory: 331.816 MB." resolution=""/>
	<Message severity="INFO" prefix="[HLS 200-111]" key="HLS_111_966" tag="RUNTIME" content="Finished Generating all RTL models: CPU user time: 0 seconds. CPU system time: 0 seconds. Elapsed time: 0.487 seconds; current allocated memory: 333.965 MB." resolution=""/>
	<Message severity="INFO" prefix="[HLS 200-111]" key="HLS_111_966" tag="RUNTIME" content="Finished Updating report files: CPU user time: 1 seconds. CPU system time: 0 seconds. Elapsed time: 0.81 seconds; current allocated memory: 338.422 MB." resolution=""/>
	<Message severity="INFO" prefix="[VHDL 208-304]" key="VHDL_304_1066" tag="" content="Generating VHDL RTL for fast_protocol." resolution=""/>
	<Message severity="INFO" prefix="[VLOG 209-307]" key="VLOG_307_1067" tag="" content="Generating Verilog RTL for fast_protocol." resolution=""/>
	<Message severity="INFO" prefix="[HLS 200-789]" key="HLS 200-789" tag="THROUGHPUT,VITIS_KERNEL" content="**** Estimated Fmax: 57.16 MHz" resolution=""/>
	<Message severity="INFO" prefix="[HLS 200-2161]" key="HLS 200-2161" tag="" content="Finished Command csynth_design Elapsed time: 00:00:22; Allocated memory: 82.836 MB." resolution=""/>
	<Message severity="INFO" prefix="[HLS 200-1510]" key="HLS 200-1510" tag="" content="Running: export_design -format ip_catalog" resolution=""/>
</Messages>
